pandoc_refheadstyle/__init__.py
pandoc_refheadstyle-0.2.2.dist-info/METADATA
pandoc_refheadstyle-0.2.2.dist-info/RECORD
pandoc_refheadstyle-0.2.2.dist-info/WHEEL
pandoc_refheadstyle-0.2.2.dist-info/top_level.txt
pandoc_refheadstyle-0.2.2.dist-info/zip-safe
