Metadata-Version: 2.1
Name: pandoc-refheadstyle
Version: 0.2.2
Summary: Pandoc filter that sets a a custom style for the reference section header.
Home-page: https://github.com/odkr/pandoc-refheadstyle/
Author: Odin Kroeger
Author-email: tqxwcv@maskr.me
License: MIT
Keywords: pandoc reference section header
Platform: UNKNOWN
Classifier: Development Status :: 4 - Beta
Classifier: License :: OSI Approved :: MIT License
Classifier: Programming Language :: Python :: 2.7
Classifier: Environment :: Console
Classifier: Operating System :: OS Independent
Classifier: Topic :: Text Processing :: Filters
Requires-Dist: panflute
